[
	{
		"date": "2023-11-01",
		"txt_en": "Never walk away from failure. On the contrary, study it carefully and imaginatively for its hidden assets.",
		"txt_cn": "遇到失败绝不要一走了之，相反的，为其隐藏的资产仔细并有想像力的研究。",
		"readmp3": "https://staticedu-wps.cache.iciba.com/audio/4b23b9815afe1540f010f28811d5f5cc.mp3"
	},
	{
		"date": "2023-11-02",
		"txt_en": "There’s never any guarantee that anyone will like you. So if anyone likes you at all, you’ve already won.",
		"txt_cn": "永远无法保证有人会喜欢你。 所以如果有人喜欢你，你就已经赢了。",
		"readmp3": "https://staticedu-wps.cache.iciba.com/audio/e0d2bd94dade1d55ea8f6de14e81d08c.mp3"
	},
	{
		"date": "2023-11-03",
		"txt_en": "If you’re offered a seat on a rocket ship, don’t ask what seat! Just get on.",
		"txt_cn": "如果有人想提供一个绝佳的成长机会给你，千万别再问对方有哪些机会选择，先把握住就对了。",
		"readmp3": "https://staticedu-wps.cache.iciba.com/audio/2ae245659a173658b91d022d7ad31e4a.mp3"
	}
]