[
	{
		"date": "2024-04-01",
		"txt_en": "It's April Fools' Day. If I believe you, I'm a noodle.",
		"txt_cn": "今天是愚人节，如果我相信你，我就是个傻瓜。",
		"readmp3": "https://staticedu-wps.cache.iciba.com/audio/1703ce72c133beecb200c19df9b6f1ce.mp3"
	},
	{
		"date": "2024-04-02",
		"txt_en": "A friend is easier lost than found.",
		"txt_cn": "得朋友难，失朋友易。",
		"readmp3": "https://staticedu-wps.cache.iciba.com/audio/37616ed52d5b68fce0ce865bf891e5ab.mp3"
	},
	{
		"date": "2024-04-03",
		"txt_en": "Patience is the best remedy.",
		"txt_cn": "忍耐是最好的药物。",
		"readmp3": "https://staticedu-wps.cache.iciba.com/audio/56ce7020e145d9c22613ada8c59db6af.mp3"
	},
	{
		"date": "2024-04-04",
		"txt_en": "A drizzling rain falls like tears on the Mourning Day.",
		"txt_cn": "清明时节雨纷纷",
		"readmp3": "https://staticedu-wps.cache.iciba.com/audio/4b6c64547ab58a0ce34aa8e22ec5d2fc.mp3"
	},
	{
		"date": "2024-04-05",
		"txt_en": "The best way to achieve a goal is to devote 100% of your time and energy to it.",
		"txt_cn": "达到目标的最好办法就是投入百分之百的时间和精力！",
		"readmp3": "https://staticedu-wps.cache.iciba.com/audio/ec95d0a3d46c8e95b14a2bfda1f492c1.mp3"
	},
	{
		"date": "2024-04-06",
		"txt_en": "A good beginning makes a good ending.",
		"txt_cn": "善始者善终。",
		"readmp3": "https://staticedu-wps.cache.iciba.com/audio/aca2581715b1cab0106966f192358cb8.mp3"
	},
	{
		"date": "2024-04-07",
		"txt_en": "Don’t lose hope.You never know what tomorrow brings.",
		"txt_cn": "别灰心，谁又知道明天会有怎样的惊喜。 --《摩登家庭》",
		"readmp3": "https://staticedu-wps.cache.iciba.com/audio/074854f4c477ab0299bfe1e3c7bfe0a2.mp3"
	},
	{
		"date": "2024-04-08",
		"txt_en": "Think less of gain and loss as long as you go all out and have a clear mind.",
		"txt_cn": "得失成败置之度外，只求竭尽所能，无愧于心。 --傅雷",
		"readmp3": "https://staticedu-wps.cache.iciba.com/audio/b56549616bcc8416479668de08346f78.mp3"
	},
	{
		"date": "2024-04-09",
		"txt_en": "The task will be hard. There may be dark days ahead.",
		"txt_cn": "任务将会困难重重，前路可能乌云密布 。",
		"readmp3": "https://staticedu-wps.cache.iciba.com/audio/04477453003559557da826744d4bc507.mp3"
	},
	{
		"date": "2024-04-10",
		"txt_en": "You can't obtain something for nothing.",
		"txt_cn": "没有付出就没有收获。 --《小美人鱼》",
		"readmp3": "https://staticedu-wps.cache.iciba.com/audio/6222fd1edf4d153a4d7c13b7896ae592.mp3"
	},
	{
		"date": "2024-04-11",
		"txt_en": "All good things come to those who wait.",
		"txt_cn": "所有美好的事物都值得等待。 --《浪人》",
		"readmp3": "https://staticedu-wps.cache.iciba.com/audio/d64bc42df0807878cd6cf0536037262d.mp3"
	},
	{
		"date": "2024-04-12",
		"txt_en": "No man is born wise or learned.",
		"txt_cn": "人非生而知之。",
		"readmp3": "https://staticedu-wps.cache.iciba.com/audio/1f83736a2f8d23bed4a0c6819c7b1065.mp3"
	},
	{
		"date": "2024-04-13",
		"txt_en": "Beauty lies in the love's eyes.",
		"txt_cn": "情人眼里出西施。",
		"readmp3": "https://staticedu-wps.cache.iciba.com/audio/c6f150c9d27bbac010ab023f5a43fed5.mp3"
	}
]