[
	{
		"date": "2025-10-01",
		"txt_en": "May our country prosper and the people live a peaceful life!",
		"txt_cn": "愿祖国繁荣富强，人民安居乐业！"
	},
	{
		"date": "2025-10-02",
		"txt_en": "To bloom is to let your scars become the map of survival.",
		"txt_cn": "绽放是让伤疤成为生存的地图。"
	},
	{
		"date": "2025-10-03",
		"txt_en": "We are not passengers of the earth, but its fleeting guardians.",
		"txt_cn": "我们并非地球的乘客，而是它短暂的守卫者。"
	},
	{
		"date": "2025-10-04",
		"txt_en": "True courage is wearing your scars as armor, not hiding them.",
		"txt_cn": "勇气是披伤痕为甲，而非遮掩。"
	},
	{
		"date": "2025-10-05",
		"txt_en": "Sacrifice is not losing a part of yourself, but planting it in someone else's future.",
		"txt_cn": "牺牲并非失去自我碎片，而是将其播种于他人的未来。"
	},
	{
		"date": "2025-10-06",
		"txt_en": "The moon hangs full, weaving our scattered hearts into a tapestry of reunion.",
		"txt_cn": "明月高悬，将散落天涯的心意编织成团圆的锦缎。"
	},
	{
		"date": "2025-10-07",
		"txt_en": "Melting glaciers are the earth's silent language of loss.",
		"txt_cn": "冰川泪滴坠入海洋，替无法言说的消亡立碑。"
	},
	{
		"date": "2025-10-08",
		"txt_en": "Broken clocks still hold the shape of time.",
		"txt_cn": "寂静是另一种计时单位。"
	},
	{
		"date": "2025-10-09",
		"txt_en": "We carry moonlight in cupped hands, afraid to spill but daring to share.",
		"txt_cn": "我们手捧点滴月色，指缝溢出的光点亮同行者的路。"
	},
	{
		"date": "2025-10-10",
		"txt_en": "Children's laughter melts winter into honey.",
		"txt_cn": "童声融化冰棱，寒冬在笑纹里结晶成糖蜜。"
	},
	{
		"date": "2025-10-11",
		"txt_en": "Fireflies map the night with borrowed starlight.",
		"txt_cn": "萤火虫用租借的星光绘制夜行地图。"
	},
	{
		"date": "2025-10-12",
		"txt_en": "Time folds wrinkles into maps of laughter.",
		"txt_cn": "时间将皱纹翻译成笑纹的年轮。"
	},
	{
		"date": "2025-10-13",
		"txt_en": "Every storm waters the seeds we forgot we planted.",
		"txt_cn": "绝望时刻往往催生意外的新芽。"
	}
]