[
	{
		"date": "2022-08-01",
		"txt_en": "The wisest mind has something yet to learn.",
		"txt_cn": "就连最智慧的人也有东西要学。",
		"author": "George Santayana",
		"share_img": "https://media-image1.baydn.com/soup_pub_image/sthbnw/7ac6676697e675482c5b0140d9aebd06.850e3717ea48f080311ee3b1248a1a47.jpeg",
		"share_url": "https://web.shanbay.com/op/quotes/2022-08-01/"
	},
	{
		"date": "2022-08-02",
		"txt_en": "We've all got both light and dark inside us. What matters is the part we choose to act on. That's who we really are.",
		"txt_cn": "我们心中都有光明和黑暗，但更重要的是我们选择哪一面。这才是我们真正的样子。",
		"author": "J.K. Rowling",
		"share_img": "https://media-image1.baydn.com/soup_pub_image/sthbnw/306b0790b78e254997d03a3b86fe66ea.e9f1f4c0f088e0cb9fe9e37e25874b18.jpeg",
		"share_url": "https://web.shanbay.com/op/quotes/2022-08-02/"
	},
	{
		"date": "2022-08-03",
		"txt_en": "Never help a child with a task at which he feels he can succeed.",
		"txt_cn": "当一个孩子觉得自己能成功完成一项任务时，千万别去帮他。",
		"author": "Maria Montessori",
		"share_img": "https://media-image1.baydn.com/soup_pub_image/sthbnw/e77fbc951be1b01540bdc789bc82a486.369a67073c326312df8e6386db24c666.jpeg",
		"share_url": "https://web.shanbay.com/op/quotes/2022-08-03/"
	},
	{
		"date": "2022-08-04",
		"txt_en": "I cannot give you the formula for success, but I can give you the formula for failure—which is: try to please everybody.",
		"txt_cn": "我不能给你成功的公式，但我可以给你失败的公式，那就是：试图取悦每个人。",
		"author": "Herbert Swope",
		"share_img": "https://media-image1.baydn.com/soup_pub_image/sthbnw/d4feb2562526dd84f6f6bf79e57f00ef.f0a5990cf1da954bfdcc216c5ae66e70.jpeg",
		"share_url": "https://web.shanbay.com/op/quotes/2022-08-04/"
	},
	{
		"date": "2022-08-05",
		"txt_en": "Wish not so much to live long as to live well.",
		"txt_cn": "与其希望活得久，不如祈盼过得好。",
		"author": "Benjamin Franklin",
		"share_img": "https://media-image1.baydn.com/soup_pub_image/sthbnw/d42f94bbbfe413dfbde066abb12ee31e.23e36fa6f78f33f2f8b5446fd1fed477.jpeg",
		"share_url": "https://web.shanbay.com/op/quotes/2022-08-05/"
	},
	{
		"date": "2022-08-06",
		"txt_en": "The expert in anything was once a beginner.",
		"txt_cn": "任何领域的专家也曾是一名初学者。",
		"author": "Helen Hayes",
		"share_img": "https://media-image1.baydn.com/soup_pub_image/sthbnw/deb4e5d2106741357a53dee57cd1d2ae.8f2942ff2670b553068d5f47509b4724.jpeg",
		"share_url": "https://web.shanbay.com/op/quotes/2022-08-06/"
	},
	{
		"date": "2022-08-07",
		"txt_en": "Be a first rate version of yourself, not a second rate version of someone else.",
		"txt_cn": "做一流的自己，不做二流的别人。",
		"author": "Judy Garland",
		"share_img": "https://media-image1.baydn.com/soup_pub_image/sthbnw/f5389c9714de1e66669400da4779858a.879966e0768ea943425105abf8ccc1de.jpeg",
		"share_url": "https://web.shanbay.com/op/quotes/2022-08-07/"
	},
	{
		"date": "2022-08-08",
		"txt_en": "You were not made to live like brute beasts, but to pursue virtue and knowledge.",
		"txt_cn": "人不应当像走兽一样活着，而应该追求知识和美德。",
		"author": "Dante Alighieri",
		"share_img": "https://media-image1.baydn.com/soup_pub_image/sthbnw/487e8f9edbf579019a22e9dfc3e43e6f.e1b9b67f9b69c6aa02b690e74958fd7f.jpeg",
		"share_url": "https://web.shanbay.com/op/quotes/2022-08-08/"
	},
	{
		"date": "2022-08-09",
		"txt_en": "Shallow men believe in luck. Strong men believe in cause and effect.",
		"txt_cn": "浅薄者相信运气；有能力的人相信因果。",
		"author": "Ralph Waldo Emerson",
		"share_img": "https://media-image1.baydn.com/soup_pub_image/sthbnw/128fbc2bb9bc06f617d5c9951f4042eb.3dc21f7fc3f8950c6d36e8905782b26b.jpeg",
		"share_url": "https://web.shanbay.com/op/quotes/2022-08-09/"
	},
	{
		"date": "2022-08-10",
		"txt_en": "Things are never as bad as they seem.",
		"txt_cn": "事情永远不会像它看起来那样糟糕。",
		"author": "《杀死一只知更鸟》",
		"share_img": "https://media-image1.baydn.com/soup_pub_image/sthbnw/8f19aa03b0e54b5e1c7b826f396ba7c9.067bc4040b814b869515dbfb61f88c00.jpeg",
		"share_url": "https://web.shanbay.com/op/quotes/2022-08-10/"
	},
	{
		"date": "2022-08-11",
		"txt_en": "All that is necessary for the triumph of evil is that good men do nothing.",
		"txt_cn": "欲使恶人得胜，只需好人袖手旁观。",
		"author": "Edmund Burke",
		"share_img": "https://media-image1.baydn.com/soup_pub_image/sthbnw/c9760cf49011d05757c0b2242b614664.f6b71ee7330aee1fae42d49008964754.jpeg",
		"share_url": "https://web.shanbay.com/op/quotes/2022-08-11/"
	},
	{
		"date": "2022-08-12",
		"txt_en": "He who loses wealth loses much; he who loses a friend loses more; but he who loses courage loses all.",
		"txt_cn": "失去财产的人损失很大，失去朋友的人损失更多，而失去勇气的人则失去了一切。",
		"author": "Cervantes",
		"share_img": "https://media-image1.baydn.com/soup_pub_image/sthbnw/9623aec3d5934686510906f7669d728f.44b3da2d21062b1519b4b40e4982c2d8.jpeg",
		"share_url": "https://web.shanbay.com/op/quotes/2022-08-12/"
	},
	{
		"date": "2022-08-13",
		"txt_en": "Be patient with yourself. Self-growth is tender; it's holy ground. There's no greater investment.",
		"txt_cn": "要对自己有耐心，自我成长是温柔的过程，是神圣之地，也是最有价值的投资。",
		"author": "Stephen Covey",
		"share_img": "https://media-image1.baydn.com/soup_pub_image/sthbnw/5cdccc3f351cb1891a1349f30af12b6f.03aa101fa8cdd4f1510d75a223115aa3.jpeg",
		"share_url": "https://web.shanbay.com/op/quotes/2022-08-13/"
	},
	{
		"date": "2022-08-14",
		"txt_en": "Reprove thy friend privately; commend him publicly.",
		"txt_cn": "在私下批评你的朋友，在公开场合赞扬他。",
		"author": "Solon",
		"share_img": "https://media-image1.baydn.com/soup_pub_image/sthbnw/ba6ffced0e30ab2b0a9bde23de579708.2aabc9925f14b72807712936452934b1.jpeg",
		"share_url": "https://web.shanbay.com/op/quotes/2022-08-14/"
	},
	{
		"date": "2022-08-15",
		"txt_en": "No matter how small and unimportant what we are doing may seem, if we do it well, it may soon become the step that will lead us to better things.",
		"txt_cn": "不管我们现在所做的事看起来有多么的微不足道或不重要，如果我们认真地做，它可能很快就会引领我们通向美好事物。",
		"author": "Channing Pollock",
		"share_img": "https://media-image1.baydn.com/soup_pub_image/sthbnw/936d502b22de61a0eb655b711b23672e.4d0b07dc5a6eae1d9e3ad8563610bf39.jpeg",
		"share_url": "https://web.shanbay.com/op/quotes/2022-08-15/"
	},
	{
		"date": "2022-08-16",
		"txt_en": "The future has several names. For the weak, it is the impossible. For the fainthearted, it is the unknown. For the thoughtful and valiant, it is the ideal.",
		"txt_cn": "未来有几个名字：对软弱的人来说，它叫不可能；对胆怯懦弱的人来说，它叫未知；对于深思熟虑且有勇气的人来说，它叫理想。",
		"author": "Victor Hugo",
		"share_img": "https://media-image1.baydn.com/soup_pub_image/sthbnw/17c6476c22dd6e7c40b0192d42d674b3.af0a722758b221057e1170375c2fbf55.jpeg",
		"share_url": "https://web.shanbay.com/op/quotes/2022-08-16/"
	},
	{
		"date": "2022-08-17",
		"txt_en": "A person can succeed at almost anything for which they have unlimited enthusiasm.",
		"txt_cn": "只要有无限的热情，一个人几乎可以在任何事情上取得成功。",
		"author": "Charles M. Schwab",
		"share_img": "https://media-image1.baydn.com/soup_pub_image/sthbnw/50fb148530862f2435cbc9b922b69151.2e6988ce59766745fbc6451686f56892.jpeg",
		"share_url": "https://web.shanbay.com/op/quotes/2022-08-17/"
	},
	{
		"date": "2022-08-18",
		"txt_en": "You can do anything you decide to do. You can act to change and control your life; and the procedure, the process, is its own reward.",
		"txt_cn": "你可以做任何你决定的事，你可以采取行动改变或控制你的人生；而这过程，本身就是报偿。",
		"author": "Amelia Earhart",
		"share_img": "https://media-image1.baydn.com/soup_pub_image/sthbnw/c33b23a5259a26f50f05ee081b367d05.a2011ba9e60e0019c642d11bca0d1a22.jpeg",
		"share_url": "https://web.shanbay.com/op/quotes/2022-08-18/"
	},
	{
		"date": "2022-08-19",
		"txt_en": "Those who bring sunshine to the lives of others cannot keep it from themselves.",
		"txt_cn": "为他人带来阳光的人，自己也一定会沐浴在阳光下。",
		"author": "James Barrie",
		"share_img": "https://media-image1.baydn.com/soup_pub_image/sthbnw/99344f838ec456ff47b9e28ff469681a.dc106fddc2a2f22ea788158c7160f4e3.jpeg",
		"share_url": "https://web.shanbay.com/op/quotes/2022-08-19/"
	},
	{
		"date": "2022-08-20",
		"txt_en": "Most of the important things in the world have been accomplished by people who have kept on trying when there seemed to be no hope at all.",
		"txt_cn": "世界上大多数重要的事情，都是由那些在看似毫无希望时还继续努力的人完成的。",
		"author": "Dale Carnegie",
		"share_img": "https://media-image1.baydn.com/soup_pub_image/sthbnw/08b1adf7ead6de27078801c72501f527.a521962ca05c1c3d31b020cea559a459.jpeg",
		"share_url": "https://web.shanbay.com/op/quotes/2022-08-20/"
	},
	{
		"date": "2022-08-21",
		"txt_en": "Many individuals have, like uncut diamonds, shining qualities beneath a rough exterior.",
		"txt_cn": "很多人像未经雕琢的钻石，在粗糙的表面下有发光的本质。",
		"author": "Juvenal",
		"share_img": "https://media-image1.baydn.com/soup_pub_image/sthbnw/d7775b9871a8fd4a04cf9a84fcd85e15.2e8433b65021fe6a4241a18eeefb6c4c.jpeg",
		"share_url": "https://web.shanbay.com/op/quotes/2022-08-21/"
	},
	{
		"date": "2022-08-22",
		"txt_en": "At the end of the day, let there be no excuses, no explanations, no regrets.",
		"txt_cn": "在一天结束的时候，别留下任何借口、解释或悔恨。",
		"author": "Steve Maraboli",
		"share_img": "https://media-image1.baydn.com/soup_pub_image/sthbnw/e03ff3efc1d73ab2fcb4ab68a8e8fafd.443b4b0a4920c257da46e17f4ea9d7e4.jpeg",
		"share_url": "https://web.shanbay.com/op/quotes/2022-08-22/"
	},
	{
		"date": "2022-08-23",
		"txt_en": "The path to your success is not as fixed and inflexible as you think.",
		"txt_cn": "成功之路并非你想的那么死板和不可改变。",
		"author": "Misty Copeland",
		"share_img": "https://media-image1.baydn.com/soup_pub_image/sthbnw/bc963dd2832f0ccb7919b0d3ef7084c5.1d166321ff3dd81f4b60734e50ee80b8.jpeg",
		"share_url": "https://web.shanbay.com/op/quotes/2022-08-23/"
	},
	{
		"date": "2022-08-24",
		"txt_en": "It is not because things are difficult that we do not dare; it is because we do not dare that they are difficult.",
		"txt_cn": "并不是因为事情难我们才不敢去做，而是因为我们不敢做事情才难。",
		"author": "Seneca",
		"share_img": "https://media-image1.baydn.com/soup_pub_image/sthbnw/0a0bb841fe4ddf39788ee28969bd1ebb.cb2f893c41edbd6d72ee3f1461b33afe.jpeg",
		"share_url": "https://web.shanbay.com/op/quotes/2022-08-24/"
	},
	{
		"date": "2022-08-25",
		"txt_en": "There are far, far better things ahead than any we leave behind.",
		"txt_cn": "比起遗落在过去的，未来还有更加美好的在等着我们。",
		"author": "C.S. Lewis",
		"share_img": "https://media-image1.baydn.com/soup_pub_image/sthbnw/31445ba56eafc1f0d5093a02b133752a.58c7d6ce79a29506522cdeed9abe52ec.jpeg",
		"share_url": "https://web.shanbay.com/op/quotes/2022-08-25/"
	},
	{
		"date": "2022-08-26",
		"txt_en": "Without self-discipline, success is impossible, period.",
		"txt_cn": "无自律，不成功，就这样。",
		"author": "Lou Holtz",
		"share_img": "https://media-image1.baydn.com/soup_pub_image/sthbnw/da0d02aaca83d715ea84284d921d82df.3c35aa29047a97bed7a4fdddb1a8fa1a.jpeg",
		"share_url": "https://web.shanbay.com/op/quotes/2022-08-26/"
	},
	{
		"date": "2022-08-27",
		"txt_en": "I am seeking, I am striving, I am in it with all my heart.",
		"txt_cn": "我在寻找，我在努力，我全身心地投入其中。",
		"author": "Vincent van Gogh",
		"share_img": "https://media-image1.baydn.com/soup_pub_image/sthbnw/f6b13637db1c493fe188b60e8f9b500a.de2f5784730d8d437e9341d56267baa0.jpeg",
		"share_url": "https://web.shanbay.com/op/quotes/2022-08-27/"
	}
]