[
	{
		"date": "2023-02-01",
		"txt_en": "Our growth depends not on how many experiences we devour, but on how many we digest.",
		"txt_cn": "成长靠的不是经历有多丰富，而是对过往经历的细细品味和领会。",
		"author": "Ralph W. Sockman",
		"share_img": "https://media-image1.baydn.com/soup_pub_image/tkdghk/bb4faebcfe4022a44c34899dd5e5aae2.662e52f65d807b4e2bca7f889df29d1a.jpeg",
		"share_url": "https://web.shanbay.com/op/quotes/2023-02-01/"
	},
	{
		"date": "2023-02-02",
		"txt_en": "Praising what is lost makes the remembrance dear.",
		"txt_cn": "赞美已经失去的事物，让回忆变得惹人喜爱。",
		"author": "William Shakespeare",
		"share_img": "https://media-image1.baydn.com/soup_pub_image/tkdghk/603dc2aaa298c7154083fd4f5cb0d669.241fb86ce4c33cbf6bf38f7a68b31a3f.jpeg",
		"share_url": "https://web.shanbay.com/op/quotes/2023-02-02/"
	},
	{
		"date": "2023-02-03",
		"txt_en": "The more we do, the more we can do.",
		"txt_cn": "我们做的越多，能做的也就越多。",
		"author": "William Hazlitt",
		"share_img": "https://media-image1.baydn.com/soup_pub_image/tkdghk/e6bed678ec4114fd7c2714352f212f48.114d49e6ff40c20729a8bcbea3029c8b.jpeg",
		"share_url": "https://web.shanbay.com/op/quotes/2023-02-03/"
	},
	{
		"date": "2023-02-04",
		"txt_en": "I'm not telling you it is going to be easy, I'm telling you it's going to be worth it.",
		"txt_cn": "我不会告诉你这个过程很容易。我只会说，这一切都是值得的。",
		"author": "Art Williams",
		"share_img": "https://media-image1.baydn.com/soup_pub_image/tkdghk/d760480d6b70604f2afd63ef0996c640.88d892a5a941f2ae0552ede9cdf8aa98.jpeg",
		"share_url": "https://web.shanbay.com/op/quotes/2023-02-04/"
	},
	{
		"date": "2023-02-05",
		"txt_en": "Keep a little fire burning; however small, however hidden.",
		"txt_cn": "让心中的火苗一直燃烧吧，不管那有多微弱，不管藏得有多深。",
		"author": "Cormac McCarthy",
		"share_img": "https://media-image1.baydn.com/soup_pub_image/tkdghk/d5a366d29b170bd1f6beeccdc2fbf3e8.d4e1e94fb23607669d9a7fe416879350.jpeg",
		"share_url": "https://web.shanbay.com/op/quotes/2023-02-05/"
	},
	{
		"date": "2023-02-06",
		"txt_en": "Nothing you wear is more important than your smile.",
		"txt_cn": "不管如何穿戴，都不比带上你的微笑。",
		"author": "Connie Stevens",
		"share_img": "https://media-image1.baydn.com/soup_pub_image/tkdghk/17f47c7bcc5dec3050ed454c2b388e3d.b928329fba3e32728b800b2c85a58c95.jpeg",
		"share_url": "https://web.shanbay.com/op/quotes/2023-02-06/"
	},
	{
		"date": "2023-02-07",
		"txt_en": "An aim in life is the only fortune worth finding.",
		"txt_cn": "生活的目标，是唯一值得我们去寻找的财富。",
		"author": "Robert Louis Stevenson",
		"share_img": "https://media-image1.baydn.com/soup_pub_image/tkdghk/dc850e35cdf76b6ff070f0d9b0fb9296.cff01c9a1e3adac54b0ab9d2537caf7b.jpeg",
		"share_url": "https://web.shanbay.com/op/quotes/2023-02-07/"
	},
	{
		"date": "2023-02-08",
		"txt_en": "Promise yourself to be so strong that nothing can disturb your peace of mind.",
		"txt_cn": "对自己承诺：要强大到任何事情都无法破坏你内心的平和。 ​​​​",
		"author": "Christian D. Larson",
		"share_img": "https://media-image1.baydn.com/soup_pub_image/tkdghk/6b03fd0d60ddbc0d8a98f52ef99263c6.0a17faff7fe515f0e39f3ccae7fcc9c6.jpeg",
		"share_url": "https://web.shanbay.com/op/quotes/2023-02-08/"
	},
	{
		"date": "2023-02-09",
		"txt_en": "We are the hero of our own story.",
		"txt_cn": "我们都是我们自己故事里的英雄。",
		"author": "Mary McCarthy",
		"share_img": "https://media-image1.baydn.com/soup_pub_image/tkdghk/a6c6969f8e66d43ffa9fd56551c7a4ff.a38ede3ba837e5cea9b4851160c84603.jpeg",
		"share_url": "https://web.shanbay.com/op/quotes/2023-02-09/"
	},
	{
		"date": "2023-02-10",
		"txt_en": "Being brave means knowing that when you fail, you don't fail forever.",
		"txt_cn": "勇敢就是知道即使你失败了，你也不是永远失败。",
		"author": "Lana Del Rey",
		"share_img": "https://media-image1.baydn.com/soup_pub_image/tkdghk/b6218af7c2ee63ed54f5062dc2102051.c8a65962e131dc88f856252ed3ea607a.jpeg",
		"share_url": "https://web.shanbay.com/op/quotes/2023-02-10/"
	},
	{
		"date": "2023-02-11",
		"txt_en": "Nothing great in the world has been accomplished without passion.",
		"txt_cn": "世上没有任何伟业的成就能够离得开激情。",
		"author": "黑格尔",
		"share_img": "https://media-image1.baydn.com/soup_pub_image/tkdghk/0314e838d967642157078b4bfe1df10b.144ef4080b7cb7ce42c6640d0e48ea83.jpeg",
		"share_url": "https://web.shanbay.com/op/quotes/2023-02-11/"
	},
	{
		"date": "2023-02-12",
		"txt_en": "Instead of wondering when your next vacation is, maybe you should set up a life you don't need to escape from.",
		"txt_cn": "与其期盼下一次假期，不如创造一种不需要逃离的生活。",
		"author": "Seth Godin",
		"share_img": "https://media-image1.baydn.com/soup_pub_image/tkdghk/e7f786840da80d8e9c3a9fc5ea5bcd7b.efc2d7be99bec3a08015fa54c71bdbba.jpeg",
		"share_url": "https://web.shanbay.com/op/quotes/2023-02-12/"
	},
	{
		"date": "2023-02-13",
		"txt_en": "It's never too late to be what you might have been.",
		"txt_cn": "成为你所要成为的人，永远都不嫌迟。",
		"author": "George Eliot",
		"share_img": "https://media-image1.baydn.com/soup_pub_image/tkdghk/9364f97073bc77e4855597ef97a9faea.3d74362f06bccdf2520ebe82472f5640.jpeg",
		"share_url": "https://web.shanbay.com/op/quotes/2023-02-13/"
	},
	{
		"date": "2023-02-14",
		"txt_en": "Pure love and suspicion cannot dwell together: at the door where the latter enters, the former makes its exit.",
		"txt_cn": "纯洁的爱情和猜疑水火不容：起了疑心，就会丢了爱情。",
		"author": "Alexandre Dumas",
		"share_img": "https://media-image1.baydn.com/soup_pub_image/tkdghk/9adc1e0f3eb4cdba7bd7ba938a87dc9c.febc05ceebff7e98811abda6287b25f5.jpeg",
		"share_url": "https://web.shanbay.com/op/quotes/2023-02-14/"
	},
	{
		"date": "2023-02-15",
		"txt_en": "Growth is the only evidence of life.",
		"txt_cn": "成长是生命的唯一证据。",
		"author": "John Henry Newman",
		"share_img": "https://media-image1.baydn.com/soup_pub_image/tkdghk/663107d212ead96b311707fddeb1e8f1.89afda8279a6ef1ca3fa4ceff70dd3b2.jpeg",
		"share_url": "https://web.shanbay.com/op/quotes/2023-02-15/"
	},
	{
		"date": "2023-02-16",
		"txt_en": "Some people dream of success, while other people get up and make it happen.",
		"txt_cn": "有些人只是梦想去成功，而其他人却起身让梦想成真。",
		"author": "Wayne Huizenga",
		"share_img": "https://media-image1.baydn.com/soup_pub_image/tkdghk/a913d60ac3b7fe5eefa5c641bec7d726.76599418b27f393a2fb9e416e292bd16.jpeg",
		"share_url": "https://web.shanbay.com/op/quotes/2023-02-16/"
	},
	{
		"date": "2023-02-17",
		"txt_en": "Success is not the key to happiness. Happiness is the key to success.",
		"txt_cn": "成功并不是快乐的关键，快乐才是成功的关键。",
		"author": "Albert Schweitzer",
		"share_img": "https://media-image1.baydn.com/soup_pub_image/tkdghk/97f948c8818304a43f107c590ba88e5c.f5940493faedda48db5a3493fc6c2d00.jpeg",
		"share_url": "https://web.shanbay.com/op/quotes/2023-02-17/"
	},
	{
		"date": "2023-02-18",
		"txt_en": "The world is extremely interesting to a joyful soul.",
		"txt_cn": "对于欢欣的灵魂而言，世界充满了奇趣。",
		"author": "Alexandra Stoddard",
		"share_img": "https://media-image1.baydn.com/soup_pub_image/tkdghk/d26735dfe66d03f5cd00cd2242bdc752.e013d43a74f7540b3e39a541f07fbdd6.jpeg",
		"share_url": "https://web.shanbay.com/op/quotes/2023-02-18/"
	},
	{
		"date": "2023-02-19",
		"txt_en": "They can because they think they can.",
		"txt_cn": "他们可以，是因为他们相信自己可以。",
		"author": "Virgil",
		"share_img": "https://media-image1.baydn.com/soup_pub_image/tkdghk/4f7dce4af2601c72ad2130b09d46e5e3.6d546344f04334be2bacdc5c848dc140.jpeg",
		"share_url": "https://web.shanbay.com/op/quotes/2023-02-19/"
	},
	{
		"date": "2023-02-20",
		"txt_en": "Instead of wondering when your next vacation is, maybe you should set up a life you don't need to escape from.",
		"txt_cn": "与其期盼下一次假期，不如创造一种不需要逃离的生活。",
		"author": "Seth Godin",
		"share_img": "https://media-image1.baydn.com/soup_pub_image/tkdghk/6e5fec083e715b957a7e7a28dc77a869.7d1bffb34a7bf73b5afd075cd9e8b42d.jpeg",
		"share_url": "https://web.shanbay.com/op/quotes/2023-02-20/"
	},
	{
		"date": "2023-02-21",
		"txt_en": "Nothing great in the world has been accomplished without passion.",
		"txt_cn": "世上没有任何伟业的成就能够离得开激情。",
		"author": "黑格尔",
		"share_img": "https://media-image1.baydn.com/soup_pub_image/tkdghk/f9ab4025408e8d08d0096cad3d160e74.9d02046a526aaf4114beead79cc25cf4.jpeg",
		"share_url": "https://web.shanbay.com/op/quotes/2023-02-21/"
	},
	{
		"date": "2023-02-22",
		"txt_en": "Never give up. Expect only the best from life and take action to get it.",
		"txt_cn": "永远不要言弃。要永远只期待最好的事物，并为之付出行动。",
		"author": "Catherine Pulsifer",
		"share_img": "https://media-image1.baydn.com/soup_pub_image/tkdghk/d23570c40107eb6862242d57eb3c234e.71739ce2e7d86f550bc5622e81ba9312.jpeg",
		"share_url": "https://web.shanbay.com/op/quotes/2023-02-22/"
	},
	{
		"date": "2023-02-23",
		"txt_en": "Life is a pure flame, and we live by an invisible sun within us.",
		"txt_cn": "生命是一束纯净的火焰，我们依靠内心看不见的太阳而存在。",
		"author": "Sir Thomas Browne",
		"share_img": "https://media-image1.baydn.com/soup_pub_image/tkdghk/dbe1d7fde64678dee673956dc055dc33.844b453d83ee3538c74a9148b6a92f4c.jpeg",
		"share_url": "https://web.shanbay.com/op/quotes/2023-02-23/"
	},
	{
		"date": "2023-02-24",
		"txt_en": "I wish somebody would have told me, that someday these will be the good old days.",
		"txt_cn": "真希望有人能提早告诉我，这岁月有天会变成回忆中的美好时光。",
		"author": "Macklemore, \"Good Old Days\"",
		"share_img": "https://media-image1.baydn.com/soup_pub_image/tkdghk/b32824daee2fd71d4e2cff0db86dc916.63efebae8868d5562b15f3106467abf9.jpeg",
		"share_url": "https://web.shanbay.com/op/quotes/2023-02-24/"
	}
]