[
	{
		"date": "2025-05-01",
		"txt_en": "One way to keep momentum going is to have constantly greater goals.",
		"txt_cn": "保持前进动力的方法就是，一直拥有更远大的目标。",
		"author": "迈克尔·考达",
		"share_img": "https://media-image1.baydn.com/soup_pub_image/tkdghk/bd43f7e020ab54245091d00f3ab60ff9.07e2aa349ad022febd84ed8f88a36f79.jpeg",
		"share_url": "https://web.shanbay.com/op/quotes/2025-05-01/"
	},
	{
		"date": "2025-05-02",
		"txt_en": "Do something today that your future self will thank you for.",
		"txt_cn": "你今天做的事要让未来的你心存感激。",
		"author": "Sean Patrick Flanery",
		"share_img": "https://media-image1.baydn.com/soup_pub_image/tkdghk/751b58bfd34f2ffb457fe1e295a90b79.0be615ddfca84e75b6c838eb17568884.jpeg",
		"share_url": "https://web.shanbay.com/op/quotes/2025-05-02/"
	},
	{
		"date": "2025-05-03",
		"txt_en": "Be strong and free from fear.",
		"txt_cn": "要坚强，毫不惧怕。",
		"author": "莱拉·姬芙蒂·阿奇塔",
		"share_img": "https://media-image1.baydn.com/soup_pub_image/tkdghk/6850e097f04f91ddd52431ff89524f28.2edca0220a26abae6cd1d93dfaccf38c.jpeg",
		"share_url": "https://web.shanbay.com/op/quotes/2025-05-03/"
	},
	{
		"date": "2025-05-04",
		"txt_en": "There is no substitute for hard work. First in, last out.",
		"txt_cn": "没有什么能替代努力，要最先开始，最后离开。",
		"author": "Mary Callahan Erdoes",
		"share_img": "https://media-image1.baydn.com/soup_pub_image/tkdghk/36fdf5482751cec4a564baf20ffe8629.507e346b60ab9d3dd788bc09a63db385.jpeg",
		"share_url": "https://web.shanbay.com/op/quotes/2025-05-04/"
	}
]